<?xml version = '1.0' encoding = 'UTF-8'?>
<xl-ddm-data version="12.2.1.4.0" user="XELSYSADM" database="" exported-date="1708423976085" description="User_Lifecycle_Event_Notification_Template_And_Lookup.xml"><Lookup repo-type="RDBMS" name="Lookup.Sample.LifecycleNotification" subtype="Lookup"><LKU_UPDATE>1708421725000</LKU_UPDATE><LKU_TYPE>l</LKU_TYPE><LKU_MEANING>Lookup.Sample.LifecycleNotification</LKU_MEANING><LookupValue repo-type="RDBMS" id="LKV2505"><LKV_UPDATE>1708421725000</LKV_UPDATE><LKV_ENCODED>Template Name</LKV_ENCODED><LKV_LANGUAGE>en</LKV_LANGUAGE><LKV_COUNTRY>US</LKV_COUNTRY><LKV_DISABLED>0</LKV_DISABLED><LKV_DECODED>User Lifecycle Event Notification</LKV_DECODED></LookupValue><LookupValue repo-type="RDBMS" id="LKV2506"><LKV_UPDATE>1708421725000</LKV_UPDATE><LKV_ENCODED>Recipient Emails</LKV_ENCODED><LKV_LANGUAGE>en</LKV_LANGUAGE><LKV_COUNTRY>US</LKV_COUNTRY><LKV_DISABLED>0</LKV_DISABLED><LKV_DECODED>test1@example.com,test2@example.com</LKV_DECODED></LookupValue><LookupValue repo-type="RDBMS" id="LKV2507"><LKV_UPDATE>1708421725000</LKV_UPDATE><LKV_ENCODED>Self Recipient</LKV_ENCODED><LKV_LANGUAGE>en</LKV_LANGUAGE><LKV_COUNTRY>US</LKV_COUNTRY><LKV_DISABLED>0</LKV_DISABLED><LKV_DECODED>True</LKV_DECODED></LookupValue><LookupValue repo-type="RDBMS" id="LKV2508"><LKV_UPDATE>1708421725000</LKV_UPDATE><LKV_ENCODED>User State</LKV_ENCODED><LKV_LANGUAGE>en</LKV_LANGUAGE><LKV_COUNTRY>US</LKV_COUNTRY><LKV_DISABLED>0</LKV_DISABLED><LKV_DECODED>DISABLED</LKV_DECODED></LookupValue></Lookup><NOTIFICATIONTEMPLATE repo-type="RDBMS" name="User Lifecycle Event Notification"><CREATEUSER>1</CREATEUSER><SNMPSUPPORTED>n</SNMPSUPPORTED><CREATIONDATE>1708420930597</CREATIONDATE><DATALEVEL>0</DATALEVEL><DESCRIPTION>User Lifecycle Event Notification</DESCRIPTION><EVENTNAME>RequestStatusChange</EVENTNAME><LASTUSER>1</LASTUSER><LASTUPDATED>1708420930597</LASTUPDATED><LOCALTEMPLATE repo-type="RDBMS" id="LOCALTEMPLATE521"><CREATEUSER>1</CREATEUSER><SHORTMESSAGE>Lifecyle Event Notification</SHORTMESSAGE><CONTENTTYPE>text/plain</CONTENTTYPE><CREATIONDATE>1708420931028</CREATIONDATE><LOCALE>en_US</LOCALE><DATALEVEL>0</DATALEVEL><ENCODING>ISO-8859-1</ENCODING><SUBJECT>Lifecyle Event Notification</SUBJECT><LONGMESSAGE>Hi $display_name,

Your account has recently been $user_state in OIM. Please contact an administrator if you think this action is unjustified.

Kind regards,
The OIM admin team</LONGMESSAGE><LASTUSER>1</LASTUSER><LASTUPDATED>1708420931028</LASTUPDATED></LOCALTEMPLATE></NOTIFICATIONTEMPLATE></xl-ddm-data>